synthetic_generator/__init__.py
synthetic_generator/cli.py
synthetic_generator/quick.py
synthetic_generator/attribute/__init__.py
synthetic_generator/attribute/base.py
synthetic_generator/dtype/__init__.py
synthetic_generator/dtype/base.py
synthetic_generator/dtype/float.py
synthetic_generator/dtype/int.py
synthetic_generator/export/__init__.py
synthetic_generator/export/database.py
synthetic_generator/export/formats.py
synthetic_generator/generators/__init__.py
synthetic_generator/generators/base.py
synthetic_generator/generators/constraints.py
synthetic_generator/generators/correlations.py
synthetic_generator/generators/distributions.py
synthetic_generator/generators/temporal_generators.py
synthetic_generator/generators/text_generators.py
synthetic_generator/input/__init__.py
synthetic_generator/input/base.py
synthetic_generator/privacy/__init__.py
synthetic_generator/privacy/anonymization.py
synthetic_generator/privacy/differential_privacy.py
synthetic_generator/schemas/__init__.py
synthetic_generator/schemas/base.py
synthetic_generator/schemas/inference.py
synthetic_generator/schemas/templates.py
synthetic_generator/utils/__init__.py
synthetic_generator/utils/package_mana.py
synthetic_generator/utils/timer.py
synthetic_generator/validate_args/__init__.py
synthetic_generator/validate_args/base.py
synthetic_generator/web/__init__.py
synthetic_generator/web/api.py
synthetic_generator/web/app.py
synthetic_generator-0.1.9.dist-info/licenses/LICENSE.txt
synthetic_generator-0.1.9.dist-info/METADATA
synthetic_generator-0.1.9.dist-info/WHEEL
synthetic_generator-0.1.9.dist-info/entry_points.txt
synthetic_generator-0.1.9.dist-info/top_level.txt
synthetic_generator-0.1.9.dist-info/RECORD
