Metadata-Version: 2.4
Name: synthetic-generator
Version: 0.1.9
Summary: Synthetic Data Generator for Machine Learning Pipelines
Author-email: Vo Hoang Nhat Khang <nhatkhangdtp@gmail.com>
Maintainer-email: Vo Hoang Nhat Khang <nhatkhangdtp@gmail.com>
License: MIT License
Project-URL: Homepage, https://github.com/nhatkhangcs/syngen.git
Project-URL: Repository, https://github.com/nhatkhangcs/syngen.git
Classifier: License :: OSI Approved :: MIT License
Classifier: Development Status :: 1 - Planning
Classifier: Intended Audience :: Developers
Classifier: Intended Audience :: Education
Classifier: Intended Audience :: End Users/Desktop
Classifier: Intended Audience :: Financial and Insurance Industry
Classifier: Intended Audience :: Healthcare Industry
Classifier: Intended Audience :: Science/Research
Classifier: Intended Audience :: Telecommunications Industry
Classifier: Operating System :: OS Independent
Classifier: Programming Language :: Python :: 3 :: Only
Classifier: Programming Language :: Python :: 3.8
Classifier: Programming Language :: Python :: 3.9
Classifier: Programming Language :: Python :: 3.10
Classifier: Programming Language :: Python :: 3.11
Classifier: Programming Language :: Python :: 3.12
Classifier: Programming Language :: Python :: Implementation
Classifier: Topic :: Scientific/Engineering :: Artificial Intelligence
Classifier: Topic :: Software Development
Classifier: Topic :: Software Development :: Libraries :: Python Modules
Requires-Python: <=3.13,>=3.8
License-File: LICENSE.txt
Requires-Dist: pandas>=1.5.0
Requires-Dist: pydantic>=2.0.0
Requires-Dist: numpy>=1.20.0
Requires-Dist: scipy>=1.8.0
Requires-Dist: openpyxl>=3.0.0
Provides-Extra: dev
Requires-Dist: setuptools>=75.1.0; extra == "dev"
Requires-Dist: wheel>=0.44.0; extra == "dev"
Requires-Dist: twine; extra == "dev"
Requires-Dist: build; extra == "dev"
Requires-Dist: pylint==2.17.7; extra == "dev"
Requires-Dist: mypy==1.4.1; extra == "dev"
Requires-Dist: jupyter>=1.1.1; extra == "dev"
Requires-Dist: pytest==8.3.3; extra == "dev"
Provides-Extra: test
Requires-Dist: pytest==8.3.3; extra == "test"
Provides-Extra: web
Requires-Dist: flask>=2.3.0; extra == "web"
Requires-Dist: flask-cors>=4.0.0; extra == "web"
Dynamic: license-file
